mollie/__init__.py
mollie/_hooks/__init__.py
mollie/_hooks/registration.py
mollie/_hooks/sdkhooks.py
mollie/_hooks/types.py
mollie/_version.py
mollie/balances.py
mollie/basesdk.py
mollie/capabilities.py
mollie/captures.py
mollie/chargebacks.py
mollie/client_links.py
mollie/clients.py
mollie/customers.py
mollie/delayed_routing.py
mollie/httpclient.py
mollie/invoices.py
mollie/mandates.py
mollie/methods.py
mollie/models/__init__.py
mollie/models/apierror.py
mollie/models/cancel_paymentop.py
mollie/models/cancel_refundop.py
mollie/models/cancel_subscriptionop.py
mollie/models/create_captureop.py
mollie/models/create_client_linkop.py
mollie/models/create_customer_paymentop.py
mollie/models/create_customerop.py
mollie/models/create_mandateop.py
mollie/models/create_order_refundop.py
mollie/models/create_payment_linkop.py
mollie/models/create_paymentop.py
mollie/models/create_profileop.py
mollie/models/create_refundop.py
mollie/models/create_subscriptionop.py
mollie/models/create_webhookop.py
mollie/models/delete_customerop.py
mollie/models/delete_payment_linkop.py
mollie/models/delete_profileop.py
mollie/models/delete_webhookop.py
mollie/models/get_balance_reportop.py
mollie/models/get_balanceop.py
mollie/models/get_captureop.py
mollie/models/get_chargebackop.py
mollie/models/get_clientop.py
mollie/models/get_current_organizationop.py
mollie/models/get_current_profileop.py
mollie/models/get_customerop.py
mollie/models/get_invoiceop.py
mollie/models/get_mandateop.py
mollie/models/get_methodop.py
mollie/models/get_next_settlementop.py
mollie/models/get_onboarding_statusop.py
mollie/models/get_open_settlementop.py
mollie/models/get_organizationop.py
mollie/models/get_partner_statusop.py
mollie/models/get_payment_link_paymentsop.py
mollie/models/get_payment_linkop.py
mollie/models/get_paymentop.py
mollie/models/get_permissionop.py
mollie/models/get_primary_balanceop.py
mollie/models/get_profileop.py
mollie/models/get_refundop.py
mollie/models/get_settlement_capturesop.py
mollie_api_python_alpha-0.5.8.dist-info/METADATA
mollie_api_python_alpha-0.5.8.dist-info/WHEEL
mollie_api_python_alpha-0.5.8.dist-info/RECORD
